tuber/__init__.py
tuber/_version.py
tuber/client.py
tuber/codecs.py
tuber/schema.py
tuber/server.py
tuber_client-0.18.3.dist-info/licenses/LICENSE
tuber_client-0.18.3.dist-info/METADATA
tuber_client-0.18.3.dist-info/WHEEL
tuber_client-0.18.3.dist-info/top_level.txt
tuber_client-0.18.3.dist-info/RECORD
