Metadata-Version: 2.4
Name: tuber-client
Version: 0.18.3
Summary: Communicate with Python (or C++) objects across a LAN using something like JSON-RPC
Author-email: Graeme Smecher <gsmecher@threespeedlogic.com>
License: Copyright (c) 2023-2024 Graeme Smecher <gsmecher@threespeedlogic.com>
Project-URL: source, https://github.com/gsmecher/tuberd
Classifier: Programming Language :: Python :: 3
Classifier: License :: OSI Approved :: BSD License
Classifier: Operating System :: OS Independent
Requires-Python: >=3.8
License-File: LICENSE
Requires-Dist: requests
Requires-Dist: requests-futures
Provides-Extra: async
Requires-Dist: aiohttp; extra == "async"
Provides-Extra: cbor
Requires-Dist: cbor2; extra == "cbor"
Provides-Extra: numpy
Requires-Dist: numpy; extra == "numpy"
Dynamic: license-file
